data-checks/__init__.py
data-checks/data_checker.py
data-checks/data_types.py
data-checks/database_operations.py
data-checks/duplicates.py
data-checks/missing_values.py
slack/__init__.py
slack/slack_operations.py
utils/__init__.py
utils/common_utils.py
propreturns_data_checker_v2-0.1.3.dist-info/METADATA
propreturns_data_checker_v2-0.1.3.dist-info/WHEEL
propreturns_data_checker_v2-0.1.3.dist-info/entry_points.txt
propreturns_data_checker_v2-0.1.3.dist-info/top_level.txt
propreturns_data_checker_v2-0.1.3.dist-info/RECORD
