Metadata-Version: 2.1
Name: propreturns-data-checker-v2
Version: 0.1.3
Author: Kathan Bhavsar
Author-email: kathanbhavsar@gmail.com
Classifier: Development Status :: 3 - Alpha
Classifier: Intended Audience :: Developers
Classifier: License :: OSI Approved :: MIT License
Classifier: Programming Language :: Python :: 3
Classifier: Programming Language :: Python :: 3.6
Classifier: Programming Language :: Python :: 3.7
Classifier: Programming Language :: Python :: 3.8
Classifier: Programming Language :: Python :: 3.9
Requires-Dist: pandas
Requires-Dist: requests
Requires-Dist: sqlalchemy
Requires-Dist: click
